yumbox/__init__.py
yumbox/cache/__init__.py
yumbox/config/__init__.py
yumbox/data/__init__.py
yumbox/factory/__init__.py
yumbox/metrics/__init__.py
yumbox/nlp/__init__.py
yumbox-0.0.1.dist-info/METADATA
yumbox-0.0.1.dist-info/WHEEL
yumbox-0.0.1.dist-info/licenses/LICENSE
yumbox-0.0.1.dist-info/RECORD
