Metadata-Version: 2.4
Name: yumbox
Version: 0.0.1
Summary: Tools and utilities for fast prototyping of machine learning ideas!
Author-email: Shayan <shayaneshteharipour@gmail.com>
License: Copyright (c) 2025 Shayan Eshteharipour
License-File: LICENSE
Requires-Python: >=3.11
Requires-Dist: faiss-cpu
Requires-Dist: hazm
Requires-Dist: lxml
Requires-Dist: nltk
Requires-Dist: numpy
Requires-Dist: parsel
Requires-Dist: pillow
Requires-Dist: torch
Requires-Dist: tqdm
Requires-Dist: unicodeblock
Provides-Extra: dev
Requires-Dist: black>=23.0; extra == 'dev'
Requires-Dist: flake8>=4.0; extra == 'dev'
Requires-Dist: mypy>=0.990; extra == 'dev'
Requires-Dist: pytest>=7.0; extra == 'dev'
